blind_llama/__init__.py
blind_llama/completion.py
blind_llama/errors.py
blind_llama/logging.py
blind_llama/pb/__init__.py
blind_llama/pb/licensing_pb2.py
blind_llama/pb/licensing_pb2_grpc.py
blind_llama/request_adapters.py
blind_llama/verify.py
blind_llama-0.1.3.dist-info/METADATA
blind_llama-0.1.3.dist-info/WHEEL
blind_llama-0.1.3.dist-info/RECORD
