Metadata-Version: 2.1
Name: blind_llama
Version: 0.1.3
Summary: 
Author: Mithril Security
Author-email: contact@mithrilsecurity.io
Requires-Python: >=3.8,<4.0
Classifier: Programming Language :: Python :: 3
Classifier: Programming Language :: Python :: 3.8
Classifier: Programming Language :: Python :: 3.9
Classifier: Programming Language :: Python :: 3.10
Classifier: Programming Language :: Python :: 3.11
Requires-Dist: grpcio (==1.56.2)
Requires-Dist: grpcio-tools (==1.56.2)
Requires-Dist: protobuf (==4.24.0)
Requires-Dist: pydantic (>=2.2.0,<3.0.0)
Requires-Dist: pyjwt (>=2.7.0,<3.0.0)
Requires-Dist: pyopenssl (>=23.2.0,<24.0.0)
Requires-Dist: pyyaml (>=6.0,<7.0)
Requires-Dist: requests (>=2.28.2,<3.0.0)
Requires-Dist: rich (>=13.3.5,<14.0.0)
Requires-Dist: typer[all] (>=0.9.0,<0.10.0)
